Metadata-Version: 1.0
Name: bg-kdistro
Version: 0.1
Summary: Gaussian and Binomial distributions package
Home-page: UNKNOWN
Author: Azorji Kelechi Oliver
Author-email: kelechioliver96@gmail.com
License: UNKNOWN
Platform: UNKNOWN
